{
    "workbench.colorTheme": "Default Dark Modern",
    "cSpell.userWords": [
        "ACCIDDA",
        "Bordetella",
        "Covariate",
        "Covariates",
        "DALY",
        "Dagster",
        "Epidata",
        "Epitopes",
        "Exceedance",
        "FIPS",
        "HPAI",
        "Herpesviruses",
        "Interepidemic",
        "JHU",
        "Kedro",
        "Klebsiella",
        "Lessler",
        "MCMC",
        "MRSA",
        "Methicillin",
        "Microbiome",
        "Norovirus",
        "Ophiocordyceps",
        "Quantiles",
        "Rotavirus",
        "Rowset",
        "SEIR",
        "Slurm",
        "Trypanosomes",
        "UNC",
        "Vacca",
        "actuals",
        "acyclical",
        "arange",
        "argslist",
        "astype",
        "basenames",
        "coursera",
        "covariates",
        "cpus",
        "dataframe",
        "dtype",
        "dtypes",
        "epitope",
        "estimatible",
        "evaled",
        "flepi",
        "flepimop",
        "fomite",
        "forecastable",
        "ftype",
        "gempyor",
        "iloc",
        "infestans",
        "invlogit",
        "ipynb",
        "isin",
        "jsons",
        "linearities",
        "longleaf",
        "macroorganisms",
        "metapopulation",
        "microdata",
        "mlops",
        "newaxis",
        "nonunique",
        "nrow",
        "parameterizing",
        "personalistic",
        "phythopthora",
        "pneumoniae",
        "pytensor",
        "quantile",
        "regularizations",
        "rootview",
        "rowsets",
        "sbatch",
        "seff",
        "skipna",
        "stackoverflow",
        "stoch",
        "subpop",
        "subpops",
        "subsetted",
        "subsetting",
        "templating",
        "timeseries",
        "unitless",
        "usefixtures",
        "variolation",
        "zombied"
    ],
    "editor.rulers": [
        88,
        92,
        132
    ],
    "files.exclude": {
        "**/.jj/": true
    },
    "workbench.colorCustomizations": {
        "editorRuler.foreground": "#8E8D8F"
    },
    "terminal.integrated.profiles.osx": {
        "fish (login)": {
            "path": "/opt/homebrew/bin/fish",
            "args": [
                "--login"
            ]
        }
    },
    "terminal.integrated.defaultProfile.osx": "fish (login)",
    "terminal.integrated.shell.osx": "fish",
    "[restructuredtext]": {
        "editor.wordWrap": "on"
    },
    "[plaintext]": {
        "editor.wordWrap": "on"
    },
    "[markdown]": {
        "editor.wordWrap": "on"
    },
    "[typescript]": {
        "editor.tabSize": 2
    },
    "[javascript]": {
        "editor.tabSize": 2
    }
}
